LICENSE
MANIFEST.in
README.md
quicktest.py
settings_test.py
setup.py
django_vkontakte_groups.egg-info/PKG-INFO
django_vkontakte_groups.egg-info/SOURCES.txt
django_vkontakte_groups.egg-info/dependency_links.txt
django_vkontakte_groups.egg-info/not-zip-safe
django_vkontakte_groups.egg-info/requires.txt
django_vkontakte_groups.egg-info/top_level.txt
vkontakte_groups/__init__.py
vkontakte_groups/__init__.pyc
vkontakte_groups/admin.py
vkontakte_groups/admin.pyc
vkontakte_groups/factories.py
vkontakte_groups/factories.pyc
vkontakte_groups/forms.py
vkontakte_groups/forms.pyc
vkontakte_groups/lookups.py
vkontakte_groups/lookups.pyc
vkontakte_groups/mixins.py
vkontakte_groups/mixins.pyc
vkontakte_groups/models.py
vkontakte_groups/models.pyc
vkontakte_groups/signals.py
vkontakte_groups/signals.pyc
vkontakte_groups/tests.py
vkontakte_groups/tests.pyc
vkontakte_groups/views.py
vkontakte_groups/views.pyc
vkontakte_groups/migrations/0001_initial.py
vkontakte_groups/migrations/0001_initial.pyc
vkontakte_groups/migrations/0002_auto.py
vkontakte_groups/migrations/0003_auto.py
vkontakte_groups/migrations/0004_auto__chg_field_group_is_admin__chg_field_group_is_closed.py
vkontakte_groups/migrations/0005_auto__del_field_group_id__chg_field_group_remote_id.py
vkontakte_groups/migrations/0006_auto__add_field_group_members_count.py
vkontakte_groups/migrations/0007_auto.py
vkontakte_groups/migrations/0007_auto.pyc
vkontakte_groups/migrations/0008_auto__add_field_group_verified.py
vkontakte_groups/migrations/__init__.py
vkontakte_groups/migrations/__init__.pyc
vkontakte_groups/sql/group.postgresql_psycopg2.sql
vkontakte_groups/templates/vkontakte_groups/import_group_posts.html